{
    "topic": "Animes des années 80",
    "categories": [ "Elders" ],
    "generation_min": "1990s",
    "generation_max": "Elders",
    "questions": [
        {
            "question" : "Lequel de ces animes n'est pas sur du football ?",
            "question_timeout" : 5,
            "waiting_answer_timeout": 10,
            "answer_timeout": 3,
            "question_media" : [ "/static/sounds/countdown.mp3", "/static/images/animes/quizz_animes_annees_80.jpg" ],
            "waiting_answer_media" : [ "/static/sounds/countdown.mp3", "/static/images/animes/quizz_animes_annees_80.jpg" ],
            "answer_media" : [ "/static/sounds/timeout.mp3", "/static/images/animes/sport_billy.jpg" ],
            "wrong_answers" : [ "L'école des champions", "Olive et Tom", "But pour Rudy" ],
            "good_answer" : "Sport Billy"
        },
        {
            "question" : "Lequel de ces animes n'est pas un 'magical girls' ?",
            "question_timeout" : 5,
            "waiting_answer_timeout": 10,
            "answer_timeout": 3,
            "question_media" : [ "/static/sounds/countdown.mp3", "/static/images/animes/quizz_animes_annees_80.jpg" ],
            "waiting_answer_media" : [ "/static/sounds/countdown.mp3", "/static/images/animes/quizz_animes_annees_80.jpg" ],
            "answer_media" : [ "/static/sounds/timeout.mp3", "/static/images/animes/princesse_sarah.jpg" ],
            "wrong_answers" : [ "Sailor Moon", "Gigi", "Emi magique" ],
            "good_answer" : "Princesse Sarah"
        },
        {
            "question" : "Quelle est la race ennemis dans Albator 78 ?",
            "question_timeout" : 5,
            "waiting_answer_timeout": 10,
            "answer_timeout": 3,
            "question_media" : [ "/static/sounds/countdown.mp3", "/static/images/animes/albator_78.jpg" ],
            "waiting_answer_media" : [ "/static/sounds/countdown.mp3", "/static/images/animes/albator_78.jpg" ],
            "answer_media" : [ "/static/sounds/timeout.mp3", "/static/images/animes/reine_sylvidra.jpg" ],
            "wrong_answers" : [ "Les Humanoïdes", "Les Invides", "Les Cyborgs" ],
            "good_answer" : "Les Sylvidres"
        },
        {
            "question" : "Dans La Bataille des Planètes les héros sont membres de quel organisation ?",
            "question_timeout" : 5,
            "waiting_answer_timeout": 10,
            "answer_timeout": 3,
            "question_media" : [ "/static/sounds/countdown.mp3", "/static/images/animes/la_bataille_des_planetes.jpg" ],
            "waiting_answer_media" : [ "/static/sounds/countdown.mp3", "/static/images/animes/la_bataille_des_planetes.jpg" ],
            "answer_media" : [ "/static/sounds/timeout.mp3", "/static/images/animes/la_force_g.jpg" ],
            "wrong_answers" : [ "Les Bioman", "Les Power Rangers", "L'équipe Z" ],
            "good_answer" : "La Force G"
        },
        {
            "question" : "Quelle est la phrase culte de Calimero ?",
            "question_timeout" : 5,
            "waiting_answer_timeout": 10,
            "answer_timeout": 3,
            "question_media" : [ "/static/sounds/countdown.mp3", "/static/images/animes/calimero.jpg" ],
            "waiting_answer_media" : [ "/static/sounds/countdown.mp3", "/static/images/animes/calimero.jpg" ],
            "answer_media" : [ "/static/sounds/timeout.mp3", "/static/images/animes/calimero_injuste.jpg" ],
            "wrong_answers" : [ "C'est vraiement pas normal", "Ca ne se fait pas", "C'est totalement injuste" ],
            "good_answer" : "C'est vraiement trop injuste"
        },
        {
            "question" : "Qui est la meilleure amie de Candy ?",
            "question_timeout" : 5,
            "waiting_answer_timeout": 10,
            "answer_timeout": 3,
            "question_media" : [ "/static/sounds/countdown.mp3", "/static/images/animes/candy.jpg" ],
            "waiting_answer_media" : [ "/static/sounds/countdown.mp3", "/static/images/animes/candy.jpg" ],
            "answer_media" : [ "/static/sounds/timeout.mp3", "/static/images/animes/candy_et_annie.jpg" ],
            "wrong_answers" : [ "Elisa", "Pony", "Capucin" ],
            "good_answer" : "Annie"
        },
        {
            "question" : "Quel est le titre japonais de 'Candy' ?",
            "question_timeout" : 5,
            "waiting_answer_timeout": 10,
            "answer_timeout": 3,
            "question_media" : [ "/static/sounds/countdown.mp3", "/static/images/animes/candy.jpg" ],
            "waiting_answer_media" : [ "/static/sounds/countdown.mp3", "/static/images/animes/candy.jpg" ],
            "answer_media" : [ "/static/sounds/timeout.mp3", "/static/images/animes/candy_candy.jpg" ],
            "wrong_answers" : [ "Ishitai", "Please my lady", "Shin Angel" ],
            "good_answer" : "Candy Candy"
        },
        {
            "question" : "Qui n'accompagne pas le Capitaine Caverne dans ses aventures ?",
            "question_timeout" : 5,
            "waiting_answer_timeout": 10,
            "answer_timeout": 3,
            "question_media" : [ "/static/sounds/countdown.mp3", "/static/images/animes/capitaine_caverne.jpg" ],
            "waiting_answer_media" : [ "/static/sounds/countdown.mp3", "/static/images/animes/capitaine_caverne.jpg" ],
            "answer_media" : [ "/static/sounds/timeout.mp3", "/static/images/animes/capitaine_caverne.jpg" ],
            "wrong_answers" : [ "Babette", "Brenda", "Lili" ],
            "good_answer" : "Elisa"
        },
        {
            "question" : "Qui peut changer d'apparence dans l'équipage du Capitaine Flam ?",
            "question_timeout" : 5,
            "waiting_answer_timeout": 10,
            "answer_timeout": 3,
            "question_media" : [ "/static/sounds/countdown.mp3", "/static/images/animes/capitaine_flam.jpg" ],
            "waiting_answer_media" : [ "/static/sounds/countdown.mp3", "/static/images/animes/capitaine_flam.jpg" ],
            "answer_media" : [ "/static/sounds/timeout.mp3", "/static/images/animes/capitaine_flam_mala.jpg" ],
            "wrong_answers" : [ "Simon", "Crag", "Curtis Newton" ],
            "good_answer" : "Mala"
        },
        {
            "question" : "Quel est le titre japonais de 'Capitaine Flam' ?",
            "question_timeout" : 5,
            "waiting_answer_timeout": 10,
            "answer_timeout": 3,
            "question_media" : [ "/static/sounds/countdown.mp3", "/static/images/animes/quizz_animes_annees_80.jpg" ],
            "waiting_answer_media" : [ "/static/sounds/countdown.mp3", "/static/images/animes/capitaine_flam.jpg" ],
            "answer_media" : [ "/static/sounds/timeout.mp3", "/static/images/animes/capitaine_flam_mala.jpg" ],
            "wrong_answers" : [ "Captain Blood", "Captain Fire", "Captain Jupiter" ],
            "good_answer" : "Captain Future"
        },
        {
            "question" : "Quel chevalier a tué le grand Pope dans Les Chevaliers du Zodiaque ?",
            "question_timeout" : 5,
            "waiting_answer_timeout": 10,
            "answer_timeout": 3,
            "question_media" : [ "/static/sounds/countdown.mp3", "/static/images/animes/saint_seiya/grand_pope.jpg" ],
            "waiting_answer_media" : [ "/static/sounds/countdown.mp3", "/static/images/animes/saint_seiya/grand_pope.jpg" ],
            "answer_media" : [ "/static/sounds/timeout.mp3", "/static/images/animes/saint_seiya/saga_du_gemeau.jpg" ],
            "wrong_answers" : [ "Aiolos du Sagittaire", "Dohko de la Balance", "Shura du Capricorne" ],
            "good_answer" : "Saga des Gémeaux"
        },
        {
            "question" : "Quel est le titre japonais de 'Les Chevaliers du Zodiaque' ?",
            "question_timeout" : 5,
            "waiting_answer_timeout": 10,
            "answer_timeout": 3,
            "question_media" : [ "/static/sounds/countdown.mp3", "/static/images/animes/quizz_animes_annees_80.jpg" ],
            "waiting_answer_media" : [ "/static/sounds/countdown.mp3", "/static/images/animes/saint_seiya/saint_seiya.jpg" ],
            "answer_media" : [ "/static/sounds/timeout.mp3", "/static/images/animes/les_chevaliers_du_zodiaque_saint_seiya.jpg" ],
            "wrong_answers" : [ "Fusai Hi", "Pegasus Fantasy", "Soldier Constellation" ],
            "good_answer" : "Saint Seiya"
        },
        {
            "question" : "Dans quelle équipe de Rugball était Cobra ?",
            "question_timeout" : 5,
            "waiting_answer_timeout": 10,
            "answer_timeout": 3,
            "question_media" : [ "/static/sounds/countdown.mp3", "/static/images/animes/cobra_cover.jpg" ],
            "waiting_answer_media" : [ "/static/sounds/countdown.mp3", "/static/images/animes/cobra.jpg" ],
            "answer_media" : [ "/static/sounds/timeout.mp3", "/static/images/animes/cobra_z_team.jpg" ],
            "wrong_answers" : [ "A", "S", "X" ],
            "good_answer" : "Z"
        },
        {
            "question" : "Quel numéro de maillot porte Cobra durant le Rugball ?",
            "question_timeout" : 5,
            "waiting_answer_timeout": 10,
            "answer_timeout": 3,
            "question_media" : [ "/static/sounds/countdown.mp3", "/static/images/animes/cobra_cover.jpg" ],
            "waiting_answer_media" : [ "/static/sounds/countdown.mp3", "/static/images/animes/cobra.jpg" ],
            "answer_media" : [ "/static/sounds/timeout.mp3", "/static/images/animes/cobra_z_team.jpg" ],
            "wrong_answers" : [ "1", "42", "99" ],
            "good_answer" : "8"
        },
        {
            "question" : "Quel est le pseudonyme de 'Cobra' durant le Rugball ?",
            "question_timeout" : 5,
            "waiting_answer_timeout": 10,
            "answer_timeout": 3,
            "question_media" : [ "/static/sounds/countdown.mp3", "/static/images/animes/cobra_cover.jpg" ],
            "waiting_answer_media" : [ "/static/sounds/countdown.mp3", "/static/images/animes/cobra.jpg" ],
            "answer_media" : [ "/static/sounds/timeout.mp3", "/static/images/animes/cobra_z_team.jpg" ],
            "wrong_answers" : [ "Mike Niven", "Pete Hamilton", "Will Huston" ],
            "good_answer" : "Joe Gillian"
        },
        {
            "question" : "Dans quel partie de son corps 'Cobra' cache son arme ?",
            "question_timeout" : 5,
            "waiting_answer_timeout": 10,
            "answer_timeout": 3,
            "question_media" : [ "/static/sounds/countdown.mp3", "/static/images/animes/cobra_cover.jpg" ],
            "waiting_answer_media" : [ "/static/sounds/countdown.mp3", "/static/images/animes/cobra.jpg" ],
            "answer_media" : [ "/static/sounds/timeout.mp3", "/static/images/animes/cobra_rayon_delta.jpg" ],
            "wrong_answers" : [ "sa bouche", "son bras droit", "son ventre" ],
            "good_answer" : "son bras gauche"
        },
        {
            "question" : "Comment se prénomme 'Cobra' avant de retrouver la mémoire ?",
            "question_timeout" : 5,
            "waiting_answer_timeout": 10,
            "answer_timeout": 3,
            "question_media" : [ "/static/sounds/countdown.mp3", "/static/images/animes/cobra_cover.jpg" ],
            "waiting_answer_media" : [ "/static/sounds/countdown.mp3", "/static/images/animes/cobra.jpg" ],
            "answer_media" : [ "/static/sounds/timeout.mp3", "/static/images/animes/cobra.jpg" ],
            "wrong_answers" : [ "Conrad", "Douglas", "Leonard" ],
            "good_answer" : "Johnson"
        },
        {
            "question" : "Comment s'appelle l'arme de 'Cobra' dans la version originale ?",
            "question_timeout" : 5,
            "waiting_answer_timeout": 10,
            "answer_timeout": 3,
            "question_media" : [ "/static/sounds/countdown.mp3", "/static/images/animes/cobra_cover.jpg" ],
            "waiting_answer_media" : [ "/static/sounds/countdown.mp3", "/static/images/animes/cobra.jpg" ],
            "answer_media" : [ "/static/sounds/timeout.mp3", "/static/images/animes/cobra.jpg" ],
            "wrong_answers" : [ "Crystalbeam", "Power Weapon", "Pyroarm" ],
            "good_answer" : "Psychogun"
        },
        {
            "question" : "Comment s'appelle l'arme de 'Cobra' dans la version française ?",
            "question_timeout" : 5,
            "waiting_answer_timeout": 10,
            "answer_timeout": 3,
            "question_media" : [ "/static/sounds/countdown.mp3", "/static/images/animes/cobra_cover.jpg" ],
            "waiting_answer_media" : [ "/static/sounds/countdown.mp3", "/static/images/animes/cobra.jpg" ],
            "answer_media" : [ "/static/sounds/timeout.mp3", "/static/images/animes/cobra.jpg" ],
            "wrong_answers" : [ "BFG", "rayon gamma", "rayon kinéforce" ],
            "good_answer" : "rayon delta"
        },
        {
            "question" : "Qui ne fait pas parti des Cosmocats ?",
            "question_timeout" : 5,
            "waiting_answer_timeout": 10,
            "answer_timeout": 3,
            "question_media" : [ "/static/sounds/countdown.mp3", "/static/images/animes/cosmocats.jpg" ],
            "waiting_answer_media" : [ "/static/sounds/countdown.mp3", "/static/images/animes/cosmocats.jpg" ],
            "answer_media" : [ "/static/sounds/timeout.mp3", "/static/images/animes/cosmocats.jpg" ],
            "wrong_answers" : [ "Félibelle", "Tigro", "Starlion" ],
            "good_answer" : "Hachiman"
        },
        {
            "question" : "Quel sport pratique Cynthia dans 'Cynthia ou le rythme de la vie' ?",
            "question_timeout" : 5,
            "waiting_answer_timeout": 10,
            "answer_timeout": 3,
            "question_media" : [ "/static/sounds/countdown.mp3", "/static/images/animes/cynthia_ou_le_rythme_de_la_vie.jpg" ],
            "waiting_answer_media" : [ "/static/sounds/countdown.mp3", "/static/images/animes/cynthia_ou_le_rythme_de_la_vie.jpg" ],
            "answer_media" : [ "/static/sounds/timeout.mp3", "/static/images/animes/cynthia_gymnasme.jpg" ],
            "wrong_answers" : [ "La danse", "Le volley-ball", "Le tennis" ],
            "good_answer" : "La gymnastique"
        },
        {
            "question" : "Qui est le compagnon de Dare Dare Motus ?",
            "question_timeout" : 5,
            "waiting_answer_timeout": 10,
            "answer_timeout": 3,
            "question_media" : [ "/static/sounds/countdown.mp3", "/static/images/animes/dare_dare_motus.jpg" ],
            "waiting_answer_media" : [ "/static/sounds/countdown.mp3", "/static/images/animes/dare_dare_motus.jpg" ],
            "answer_media" : [ "/static/sounds/timeout.mp3", "/static/images/animes/dare_dare_motus.jpg" ],
            "wrong_answers" : [ "Le baron Dovert", "Stiletto", "Le Colonel Z" ],
            "good_answer" : "Panikar"
        },
        {
            "question" : "Edgar est le détective",
            "question_timeout" : 5,
            "waiting_answer_timeout": 10,
            "answer_timeout": 3,
            "question_media" : [ "/static/sounds/countdown.mp3", "/static/images/animes/edgar_detective_cambrioleur_nameless.jpg" ],
            "waiting_answer_media" : [ "/static/sounds/countdown.mp3", "/static/images/animes/edgar_detective_cambrioleur_nameless.jpg" ],
            "answer_media" : [ "/static/sounds/timeout.mp3", "/static/images/animes/edgar_detective_cambrioleur.jpg" ],
            "wrong_answers" : [ "Professeur", "Inventeur", "Chercheur" ],
            "good_answer" : "Cambrioleur"
        },
        {
            "question" : "Quel instrument joue Tristan dans 'Embrasse-moi Lucile' ?",
            "question_timeout" : 5,
            "waiting_answer_timeout": 10,
            "answer_timeout": 3,
            "question_media" : [ "/static/sounds/countdown.mp3", "/static/images/animes/embrasse_moi_lucile.jpg" ],
            "waiting_answer_media" : [ "/static/sounds/countdown.mp3", "/static/images/animes/embrasse_moi_lucile_tristan.jpg" ],
            "answer_media" : [ "/static/sounds/timeout.mp3", "/static/images/animes/embrasse_moi_lucile_tristan_pianiste.jpg" ],
            "wrong_answers" : [ "Batterie", "Guitare", "Basse" ],
            "good_answer" : "Piano"
        },
        {
            "question" : "Quel est le titre japonais de 'Lucile, Amour Et Rock N Roll' ?",
            "question_timeout" : 5,
            "waiting_answer_timeout": 10,
            "answer_timeout": 3,
            "question_media" : [ "/static/sounds/countdown.mp3", "/static/images/animes/embrasse_moi_lucile.jpg" ],
            "waiting_answer_media" : [ "/static/sounds/countdown.mp3", "/static/images/animes/embrasse_moi_lucile.jpg" ],
            "answer_media" : [ "/static/sounds/timeout.mp3", "/static/images/animes/aishite_night.jpg" ],
            "wrong_answers" : [ "Candy Candy", "Shin Angel", "Urotsukidoji" ],
            "good_answer" : "Aishite Night"
        },
        {
            "question" : "Quel est le nom du groupe de musique dans 'Lucile, Amour Et Rock N Roll' ?",
            "question_timeout" : 5,
            "waiting_answer_timeout": 10,
            "answer_timeout": 3,
            "question_media" : [ "/static/sounds/countdown.mp3", "/static/images/animes/embrasse_moi_lucile.jpg" ],
            "waiting_answer_media" : [ "/static/sounds/countdown.mp3", "/static/images/animes/embrasse_moi_lucile.jpg" ],
            "answer_media" : [ "/static/sounds/timeout.mp3", "/static/images/animes/embrasse_moi_lucile_bee_hive.jpg" ],
            "wrong_answers" : [ "Black Stones", "Stardust Galaxy", "The Shooters" ],
            "good_answer" : "Bee Hive"
        },
        {
            "question" : "Qui n'est pas un compagnon de Gigi ?",
            "question_timeout" : 5,
            "waiting_answer_timeout": 10,
            "answer_timeout": 3,
            "question_media" : [ "/static/sounds/countdown.mp3", "/static/images/animes/gigi.jpg" ],
            "waiting_answer_media" : [ "/static/sounds/countdown.mp3", "/static/images/animes/gigi.jpg" ],
            "answer_media" : [ "/static/sounds/timeout.mp3", "/static/images/animes/gigi.jpg" ],
            "wrong_answers" : [ "Sindbook", "Mocha", "Pipil" ],
            "good_answer" : "Fenarinarsa"
        },
        {
            "question" : "Comment s'appelle la soeur d'Actarus dans Goldorak ?",
            "question_timeout" : 5,
            "waiting_answer_timeout": 10,
            "answer_timeout": 3,
            "question_media" : [ "/static/sounds/countdown.mp3", "/static/images/animes/goldorak_phenicia.jpg" ],
            "waiting_answer_media" : [ "/static/sounds/countdown.mp3", "/static/images/animes/goldorak_phenicia.jpg" ],
            "answer_media" : [ "/static/sounds/timeout.mp3", "/static/images/animes/goldorak_phenicia.jpg" ],
            "wrong_answers" : [ "Minas", "Akira", "Vénusia" ],
            "good_answer" : "Phénicia"
        },
        {
            "question" : "Quel est le titre japonais de 'Goldorak' ?",
            "question_timeout" : 5,
            "waiting_answer_timeout": 10,
            "answer_timeout": 3,
            "question_media" : [ "/static/sounds/countdown.mp3", "/static/images/animes/goldorak.jpg" ],
            "waiting_answer_media" : [ "/static/sounds/countdown.mp3", "/static/images/animes/goldorak.jpg" ],
            "answer_media" : [ "/static/sounds/timeout.mp3", "/static/images/animes/goldorak_ufo_robot_grendizer.jpg" ],
            "wrong_answers" : [ "Goldorak", "Mazinger Z", "Super Wars" ],
            "good_answer" : "UFO Robot Grendizer"
        },
        {
            "question" : "Comment s'appelle le sage dans Il était une fois… l'Homme ?",
            "question_timeout" : 5,
            "waiting_answer_timeout": 10,
            "answer_timeout": 3,
            "question_media" : [ "/static/sounds/countdown.mp3", "/static/images/animes/Il_etait_une_fois_l_homme.jpg" ],
            "waiting_answer_media" : [ "/static/sounds/countdown.mp3", "/static/images/animes/Il_etait_une_fois_l_homme.jpg" ],
            "answer_media" : [ "/static/sounds/timeout.mp3", "/static/images/animes/Il_etait_une_fois_l_homme.jpg" ],
            "wrong_answers" : [ "Phenomeno", "Geppeto", "Pierrot" ],
            "good_answer" : "Maestro"
        },
        {
            "question" : "Comment s'appelle le navigateur dans Jayce et les conquérants de la Lumière ?",
            "question_timeout" : 5,
            "waiting_answer_timeout": 10,
            "answer_timeout": 3,
            "question_media" : [ "/static/sounds/countdown.mp3", "/static/images/animes/jayce_et_les_conquerants_de_la_lumiere_herc.jpg" ],
            "waiting_answer_media" : [ "/static/sounds/countdown.mp3", "/static/images/animes/jayce_et_les_conquerants_de_la_lumiere_herc.jpg" ],
            "answer_media" : [ "/static/sounds/timeout.mp3", "/static/images/animes/jayce_et_les_conquerants_de_la_lumiere_herc.jpg" ],
            "wrong_answers" : [ "Ted", "James", "Spencer" ],
            "good_answer" : "Herc"
        },
        {
            "question" : "Quel est le nom de Peggy dans Jeanne et Serge ?",
            "question_timeout" : 5,
            "waiting_answer_timeout": 10,
            "answer_timeout": 3,
            "question_media" : [ "/static/sounds/countdown.mp3", "/static/images/animes/jeanne_et_serge_peggy.jpg" ],
            "waiting_answer_media" : [ "/static/sounds/countdown.mp3", "/static/images/animes/jeanne_et_serge_peggy.jpg" ],
            "answer_media" : [ "/static/sounds/timeout.mp3", "/static/images/animes/jeanne_et_serge_peggy.jpg" ],
            "wrong_answers" : [ "Takiki", "Takigawa", "Hazuki" ],
            "good_answer" : "Hayaze"
        },
        {
            "question" : "Quel est le titre japonais de 'Jeanne et Serge' ?",
            "question_timeout" : 5,
            "waiting_answer_timeout": 10,
            "answer_timeout": 3,
            "question_media" : [ "/static/sounds/countdown.mp3", "/static/images/animes/quizz_animes_annees_80.jpg" ],
            "waiting_answer_media" : [ "/static/sounds/countdown.mp3", "/static/images/animes/jeanne_et_serge.jpg" ],
            "answer_media" : [ "/static/sounds/timeout.mp3", "/static/images/animes/attacker_you.jpg" ],
            "wrong_answers" : [ "Attack No.1 !", "Esu o Nerae !", "Smash Ashita e Attack !" ],
            "good_answer" : "Attacker You !"
        },
        {
            "question" : "Dans quel groupe joue Stormer dans Jem et les Hologrammes ?",
            "question_timeout" : 5,
            "waiting_answer_timeout": 10,
            "answer_timeout": 3,
            "question_media" : [ "/static/sounds/countdown.mp3", "/static/images/animes/jem_et_les_hologrammes_misfits.jpg" ],
            "waiting_answer_media" : [ "/static/sounds/countdown.mp3", "/static/images/animes/jem_et_les_hologrammes_misfits.jpg" ],
            "answer_media" : [ "/static/sounds/timeout.mp3", "/static/images/animes/jem_et_les_hologrammes_stormer.jpg" ],
            "wrong_answers" : [ "Jem et les Hologrammes", "Les Stingers", "Les Suprêmes" ],
            "good_answer" : "Les Misfits"
        },
        {
            "question" : "Comment s'appelle le chien de Juliette dans Juliette je t'aime?",
            "question_timeout" : 5,
            "waiting_answer_timeout": 10,
            "answer_timeout": 3,
            "question_media" : [ "/static/sounds/countdown.mp3", "/static/images/animes/juliette_je_t_aime.jpg" ],
            "waiting_answer_media" : [ "/static/sounds/countdown.mp3", "/static/images/animes/juliette_je_t_aime_maxime.jpg" ],
            "answer_media" : [ "/static/sounds/timeout.mp3", "/static/images/animes/juliette_je_t_aime_maxime.jpg" ],
            "wrong_answers" : [ "Jule", "Hugo", "Stéphane" ],
            "good_answer" : "Maxime"
        },
        {
            "question" : "Quel est le titre japonais de 'Juliette je t'aime' ?",
            "question_timeout" : 5,
            "waiting_answer_timeout": 10,
            "answer_timeout": 3,
            "question_media" : [ "/static/sounds/countdown.mp3", "/static/images/animes/juliette_je_t_aime.jpg" ],
            "waiting_answer_media" : [ "/static/sounds/countdown.mp3", "/static/images/animes/juliette_je_t_aime.jpg" ],
            "answer_media" : [ "/static/sounds/timeout.mp3", "/static/images/animes/maison_ikkoku.jpg" ],
            "wrong_answers" : [ "Chambre Aishiteru", "City of love", "House Mad" ],
            "good_answer" : "Maison Ikkoku"
        },
        {
            "question" : "Qui n'est pas le frère le Ken dans Ken le Survivant ?",
            "question_timeout" : 5,
            "waiting_answer_timeout": 10,
            "answer_timeout": 3,
            "question_media" : [ "/static/sounds/countdown.mp3", "/static/images/animes/ken_le_survivant.jpg" ],
            "waiting_answer_media" : [ "/static/sounds/countdown.mp3", "/static/images/animes/ken_le_survivant.jpg" ],
            "answer_media" : [ "/static/sounds/timeout.mp3", "/static/images/animes/ken_le_survivant_ray.jpg" ],
            "wrong_answers" : [ "Raoul", "Jagger", "Toki" ],
            "good_answer" : "Ray"
        },
        {
            "question" : "Quel est le principal groupe que poursuit l'équipe du M.A.S.K. ?",
            "question_timeout" : 5,
            "waiting_answer_timeout": 10,
            "answer_timeout": 3,
            "question_media" : [ "/static/sounds/countdown.mp3", "/static/images/animes/mask.jpg" ],
            "waiting_answer_media" : [ "/static/sounds/countdown.mp3", "/static/images/animes/mask.jpg" ],
            "answer_media" : [ "/static/sounds/timeout.mp3", "/static/images/animes/quizz_animes_annees_80.jpg" ],
            "wrong_answers" : [ "DECEPTICONS", "SHINRA", "COBRA" ],
            "good_answer" : "VENOM"
        },
        {
            "question" : "Quel objet magique porte autour de son cou Madame Pepperpote ?",
            "question_timeout" : 5,
            "waiting_answer_timeout": 10,
            "answer_timeout": 3,
            "question_media" : [ "/static/sounds/countdown.mp3", "/static/images/animes/quizz_animes_annees_80.jpg" ],
            "waiting_answer_media" : [ "/static/sounds/countdown.mp3", "/static/images/animes/quizz_animes_annees_80.jpg" ],
            "answer_media" : [ "/static/sounds/timeout.mp3", "/static/images/animes/quizz_animes_annees_80.jpg" ],
            "wrong_answers" : [ "Une Cloche", "Une Timbale", "Une Tasse" ],
            "good_answer" : "Une Cuillère"
        },
        {
            "question" : "Dans les Maîtres de l'Univers que dit Musclor après 'Par le pouvoir du Crâne ancestral'?",
            "question_timeout" : 5,
            "waiting_answer_timeout": 10,
            "answer_timeout": 3,
            "question_media" : [ "/static/sounds/countdown.mp3", "/static/images/animes/quizz_animes_annees_80.jpg" ],
            "waiting_answer_media" : [ "/static/sounds/countdown.mp3", "/static/images/animes/quizz_animes_annees_80.jpg" ],
            "answer_media" : [ "/static/sounds/timeout.mp3", "/static/images/animes/quizz_animes_annees_80.jpg" ],
            "wrong_answers" : [ "Je détiens l'Epée magique !", "Je détiens la Force absolue !", "Je détiens le pouvoir de la Force !" ],
            "good_answer" : "Je détiens la Force toute puissante !"
        },
        {
            "question" : "Comment s'appelle l'asticot dans Maya l'Abeille ?",
            "question_timeout" : 5,
            "waiting_answer_timeout": 10,
            "answer_timeout": 3,
            "question_media" : [ "/static/sounds/countdown.mp3", "/static/images/animes/quizz_animes_annees_80.jpg" ],
            "waiting_answer_media" : [ "/static/sounds/countdown.mp3", "/static/images/animes/quizz_animes_annees_80.jpg" ],
            "answer_media" : [ "/static/sounds/timeout.mp3", "/static/images/animes/quizz_animes_annees_80.jpg" ],
            "wrong_answers" : [ "Flip", "Willy", "Alexandre" ],
            "good_answer" : "Max"
        },
        {
            "question" : "Comment s'appelle le professeur qui poursuit Les Minipouss ?",
            "question_timeout" : 5,
            "waiting_answer_timeout": 10,
            "answer_timeout": 3,
            "question_media" : [ "/static/sounds/countdown.mp3", "/static/images/animes/quizz_animes_annees_80.jpg" ],
            "waiting_answer_media" : [ "/static/sounds/countdown.mp3", "/static/images/animes/quizz_animes_annees_80.jpg" ],
            "answer_media" : [ "/static/sounds/timeout.mp3", "/static/images/animes/quizz_animes_annees_80.jpg" ],
            "wrong_answers" : [ "Professeur Brossard", "Professeur Mouchard", "Professeur Boulanger" ],
            "good_answer" : "Professeur Chassard"
        },
        {
            "question" : "De quel peuple Tao descend dans Les Mystérieuses Cités d'Or ?",
            "question_timeout" : 5,
            "waiting_answer_timeout": 10,
            "answer_timeout": 3,
            "question_media" : [ "/static/sounds/countdown.mp3", "/static/images/animes/quizz_animes_annees_80.jpg" ],
            "waiting_answer_media" : [ "/static/sounds/countdown.mp3", "/static/images/animes/quizz_animes_annees_80.jpg" ],
            "answer_media" : [ "/static/sounds/timeout.mp3", "/static/images/animes/quizz_animes_annees_80.jpg" ],
            "wrong_answers" : [ "Olmèques", "Incas", "Apache" ],
            "good_answer" : "Mu"
        },
        {
            "question" : "Nils Olgerson et",
            "question_timeout" : 5,
            "waiting_answer_timeout": 10,
            "answer_timeout": 3,
            "question_media" : [ "/static/sounds/countdown.mp3", "/static/images/animes/quizz_animes_annees_80.jpg" ],
            "waiting_answer_media" : [ "/static/sounds/countdown.mp3", "/static/images/animes/quizz_animes_annees_80.jpg" ],
            "answer_media" : [ "/static/sounds/timeout.mp3", "/static/images/animes/quizz_animes_annees_80.jpg" ],
            "wrong_answers" : [ "Les pélicans sauvages", "Les canards sauvages", "Les cygnes sauvages" ],
            "good_answer" : "Les oies sauvages"
        },
        {
            "question" : "Qui sont les pilotes de Zoom et Turbo dans Pole Position ?",
            "question_timeout" : 5,
            "waiting_answer_timeout": 10,
            "answer_timeout": 3,
            "question_media" : [ "/static/sounds/countdown.mp3", "/static/images/animes/quizz_animes_annees_80.jpg" ],
            "waiting_answer_media" : [ "/static/sounds/countdown.mp3", "/static/images/animes/quizz_animes_annees_80.jpg" ],
            "answer_media" : [ "/static/sounds/timeout.mp3", "/static/images/animes/quizz_animes_annees_80.jpg" ],
            "wrong_answers" : [ "Marc et Sophie", "Olive et Tom", "Lucile et Roméo" ],
            "good_answer" : "Luc et Lise"
        },
        {
            "question" : "Qui est la directrice du pensionnat dans Princesse Sarah ?",
            "question_timeout" : 5,
            "waiting_answer_timeout": 10,
            "answer_timeout": 3,
            "question_media" : [ "/static/sounds/countdown.mp3", "/static/images/animes/quizz_animes_annees_80.jpg" ],
            "waiting_answer_media" : [ "/static/sounds/countdown.mp3", "/static/images/animes/quizz_animes_annees_80.jpg" ],
            "answer_media" : [ "/static/sounds/timeout.mp3", "/static/images/animes/quizz_animes_annees_80.jpg" ],
            "wrong_answers" : [ "Madame Marie", "Madame Dufarge", "Madame Lavinia" ],
            "good_answer" : "Madame Mangin"
        },
        {
            "question" : "Dans Rémi sans famille, comment s'appelle le chien de Rémi ?",
            "question_timeout" : 5,
            "waiting_answer_timeout": 10,
            "answer_timeout": 3,
            "question_media" : [ "/static/sounds/countdown.mp3", "/static/images/animes/quizz_animes_annees_80.jpg" ],
            "waiting_answer_media" : [ "/static/sounds/countdown.mp3", "/static/images/animes/quizz_animes_annees_80.jpg" ],
            "answer_media" : [ "/static/sounds/timeout.mp3", "/static/images/animes/quizz_animes_annees_80.jpg" ],
            "wrong_answers" : [ "Zerbino", "Joli-cœur", "Vitalis" ],
            "good_answer" : "Capi"
        },
        {
            "question" : "Quel est le prénom du petit Cid  ?",
            "question_timeout" : 5,
            "waiting_answer_timeout": 10,
            "answer_timeout": 3,
            "question_media" : [ "/static/sounds/countdown.mp3", "/static/images/animes/quizz_animes_annees_80.jpg" ],
            "waiting_answer_media" : [ "/static/sounds/countdown.mp3", "/static/images/animes/quizz_animes_annees_80.jpg" ],
            "answer_media" : [ "/static/sounds/timeout.mp3", "/static/images/animes/quizz_animes_annees_80.jpg" ],
            "wrong_answers" : [ "Rudy", "Rémy", "Rony" ],
            "good_answer" : "Rody"
        },
        {
            "question" : "Comment s'appelle l'ogre géant dans Les Schtroumpfs ?",
            "question_timeout" : 5,
            "waiting_answer_timeout": 10,
            "answer_timeout": 3,
            "question_media" : [ "/static/sounds/countdown.mp3", "/static/images/animes/quizz_animes_annees_80.jpg" ],
            "waiting_answer_media" : [ "/static/sounds/countdown.mp3", "/static/images/animes/quizz_animes_annees_80.jpg" ],
            "answer_media" : [ "/static/sounds/timeout.mp3", "/static/images/animes/quizz_animes_annees_80.jpg" ],
            "wrong_answers" : [ "Cracoucass", "Balthazar", "Azraël" ],
            "good_answer" : "Grossbouf"
        },
        {
            "question" : "Les compagnons de Scooby-Doo sont Sammy, Fred, Daphné et",
            "question_timeout" : 5,
            "waiting_answer_timeout": 10,
            "answer_timeout": 3,
            "question_media" : [ "/static/sounds/countdown.mp3", "/static/images/animes/quizz_animes_annees_80.jpg" ],
            "waiting_answer_media" : [ "/static/sounds/countdown.mp3", "/static/images/animes/quizz_animes_annees_80.jpg" ],
            "answer_media" : [ "/static/sounds/timeout.mp3", "/static/images/animes/quizz_animes_annees_80.jpg" ],
            "wrong_answers" : [ "Marta", "Isa", "Eva" ],
            "good_answer" : "Véra"
        },
        {
            "question" : "Comment s'appelle le fiancé de Tam dans Signé Cat's Eyes ?",
            "question_timeout" : 5,
            "waiting_answer_timeout": 10,
            "answer_timeout": 3,
            "question_media" : [ "/static/sounds/countdown.mp3", "/static/images/animes/quizz_animes_annees_80.jpg" ],
            "waiting_answer_media" : [ "/static/sounds/countdown.mp3", "/static/images/animes/quizz_animes_annees_80.jpg" ],
            "answer_media" : [ "/static/sounds/timeout.mp3", "/static/images/animes/quizz_animes_annees_80.jpg" ],
            "wrong_answers" : [ "Quentin Asaya", "Quentin Durieux", "Quentin Chamade" ],
            "good_answer" : "Quentin Chapuis"
        },
        {
            "question" : "Comment s'appelle le professeur de Tom Sawyer ?",
            "question_timeout" : 5,
            "waiting_answer_timeout": 10,
            "answer_timeout": 3,
            "question_media" : [ "/static/sounds/countdown.mp3", "/static/images/animes/quizz_animes_annees_80.jpg" ],
            "waiting_answer_media" : [ "/static/sounds/countdown.mp3", "/static/images/animes/quizz_animes_annees_80.jpg" ],
            "answer_media" : [ "/static/sounds/timeout.mp3", "/static/images/animes/quizz_animes_annees_80.jpg" ],
            "wrong_answers" : [ "M. Potter", "M. Jean", "M. Thatcher" ],
            "good_answer" : "M. Dobbins"
        },
        {
            "question" : "Quel est l'auteur du roman Le Tour du monde en quatre-vingts jours ?",
            "question_timeout" : 5,
            "waiting_answer_timeout": 10,
            "answer_timeout": 3,
            "question_media" : [ "/static/sounds/countdown.mp3", "/static/images/animes/quizz_animes_annees_80.jpg" ],
            "waiting_answer_media" : [ "/static/sounds/countdown.mp3", "/static/images/animes/quizz_animes_annees_80.jpg" ],
            "answer_media" : [ "/static/sounds/timeout.mp3", "/static/images/animes/quizz_animes_annees_80.jpg" ],
            "wrong_answers" : [ "Victor Hugo", "Honoré de Balzac", "Emile Zola" ],
            "good_answer" : "Jules Verne"
        },
        {
            "question" : "Quel marque de jouets sponsorise les Transformers ?",
            "question_timeout" : 5,
            "waiting_answer_timeout": 10,
            "answer_timeout": 3,
            "question_media" : [ "/static/sounds/countdown.mp3", "/static/images/animes/quizz_animes_annees_80.jpg" ],
            "waiting_answer_media" : [ "/static/sounds/countdown.mp3", "/static/images/animes/quizz_animes_annees_80.jpg" ],
            "answer_media" : [ "/static/sounds/timeout.mp3", "/static/images/animes/quizz_animes_annees_80.jpg" ],
            "wrong_answers" : [ "Tomy", "Playskool", "Vtech" ],
            "good_answer" : "Hasbro"
        },
        {
            "question" : "Quel dieu condamne les humains dans Ulysse 31 ?",
            "question_timeout" : 5,
            "waiting_answer_timeout": 10,
            "answer_timeout": 3,
            "question_media" : [ "/static/sounds/countdown.mp3", "/static/images/animes/quizz_animes_annees_80.jpg" ],
            "waiting_answer_media" : [ "/static/sounds/countdown.mp3", "/static/images/animes/quizz_animes_annees_80.jpg" ],
            "answer_media" : [ "/static/sounds/timeout.mp3", "/static/images/animes/quizz_animes_annees_80.jpg" ],
            "wrong_answers" : [ "Athena", "Poséidon", "Cyclope" ],
            "good_answer" : "Zeus"
        },
        {
            "question" : "Dans quel pays se passe l'action de 'Rémi sans famille' ?",
            "question_timeout" : 5,
            "waiting_answer_timeout": 10,
            "answer_timeout": 3,
            "question_media" : [ "/static/sounds/countdown.mp3", "/static/images/animes/quizz_animes_annees_80.jpg" ],
            "waiting_answer_media" : [ "/static/sounds/countdown.mp3", "/static/images/animes/quizz_animes_annees_80.jpg" ],
            "answer_media" : [ "/static/sounds/timeout.mp3", "/static/images/animes/quizz_animes_annees_80.jpg" ],
            "wrong_answers" : [ "L'Allemagne", "L'Italie", "L'Angleterre" ],
            "good_answer" : "La France"
        },
        {
            "question" : "Quel est le titre japonais de 'Olive et Tom' ?",
            "question_timeout" : 5,
            "waiting_answer_timeout": 10,
            "answer_timeout": 3,
            "question_media" : [ "/static/sounds/countdown.mp3", "/static/images/animes/captain_tsubasa/olive_et_tom.jpg" ],
            "waiting_answer_media" : [ "/static/sounds/countdown.mp3", "/static/images/animes/captain_tsubasa/olive_et_tom.jpg" ],
            "answer_media" : [ "/static/sounds/timeout.mp3", "/static/images/animes/captain_tsubasa/captain_tsubasa.jpg" ],
            "wrong_answers" : [ "Ganbare ! Kickers", "Hitachi No Joe", "Super Soccer" ],
            "good_answer" : "Captain Tsubasa"
        },
        {
            "question" : "Quel est le titre japonais de 'Nicky Larson' ?",
            "question_timeout" : 5,
            "waiting_answer_timeout": 10,
            "answer_timeout": 3,
            "question_media" : [ "/static/sounds/countdown.mp3", "/static/images/animes/quizz_animes_annees_80.jpg" ],
            "waiting_answer_media" : [ "/static/sounds/countdown.mp3", "/static/images/animes/nicky_larson.jpg" ],
            "answer_media" : [ "/static/sounds/timeout.mp3", "/static/images/animes/city_hunter.jpg" ],
            "wrong_answers" : [ "Boku wa tomodachi ga sukunai", "Cops", "Guilty Country" ],
            "good_answer" : "City Hunter"
        },
        {
            "question" : "Quel est le titre français de cet anime ?",
            "question_timeout" : 5,
            "waiting_answer_timeout": 10,
            "answer_timeout": 3,
            "question_media" : [ "/static/sounds/countdown.mp3", "/static/images/animes/quizz_animes_annees_80.jpg" ],
            "waiting_answer_media" : [ "/static/sounds/countdown.mp3", "/static/images/animes/lamu_urusei_yatsura.jpg" ],
            "answer_media" : [ "/static/sounds/timeout.mp3", "/static/images/animes/lamu.jpg" ],
            "wrong_answers" : [ "Ranma 1/2", "Juliette je t'aime", "Candy" ],
            "good_answer" : "Lamu"
        },
        {
            "question" : "Quel art martial pratique 'Judo Boy' ?",
            "question_timeout" : 5,
            "waiting_answer_timeout": 10,
            "answer_timeout": 3,
            "question_media" : [ "/static/sounds/countdown.mp3", "/static/images/animes/quizz_animes_annees_80.jpg" ],
            "waiting_answer_media" : [ "/static/sounds/countdown.mp3", "/static/images/animes/judo_boy.jpg" ],
            "answer_media" : [ "/static/sounds/timeout.mp3", "/static/images/animes/judo_boy.jpg" ],
            "wrong_answers" : [ "du Judo", "du Karaté", "du Taekwondo" ],
            "good_answer" : "du Jiujitsu"
        },
        {
            "question" : "Comment se déplace 'Judo Boy' ?",
            "question_timeout" : 5,
            "waiting_answer_timeout": 10,
            "answer_timeout": 3,
            "question_media" : [ "/static/sounds/countdown.mp3", "/static/images/animes/quizz_animes_annees_80.jpg" ],
            "waiting_answer_media" : [ "/static/sounds/countdown.mp3", "/static/images/animes/judo_boy.jpg" ],
            "answer_media" : [ "/static/sounds/timeout.mp3", "/static/images/animes/judo_boy_en_moto.jpg" ],
            "wrong_answers" : [ "en camion", "en taxi", "en voiture" ],
            "good_answer" : "en moto"
        },
        {
            "question" : "Qui interprète la chanson de générique de 'Rody le Petit Cid' ?",
            "question_timeout" : 5,
            "waiting_answer_timeout": 10,
            "answer_timeout": 3,
            "question_media" : [ "/static/sounds/countdown.mp3", "/static/images/animes/quizz_animes_annees_80.jpg" ],
            "waiting_answer_media" : [ "/static/sounds/countdown.mp3", "/static/images/animes/rody_le_petit_cid.jpg" ],
            "answer_media" : [ "/static/sounds/timeout.mp3", "/static/images/animes/rody_le_petit_cid.jpg" ],
            "wrong_answers" : [ "Antoine de Caunes", "Didier Barbelivien", "Pierre Desproges" ],
            "good_answer" : "Thierry le Luron"
        },
        {
            "question" : "Quel sport est pratiqué dans le dessin animé 'Les attaquantes' ?",
            "question_timeout" : 5,
            "waiting_answer_timeout": 10,
            "answer_timeout": 3,
            "question_media" : [ "/static/sounds/countdown.mp3", "/static/images/animes/quizz_animes_annees_80.jpg" ],
            "waiting_answer_media" : [ "/static/sounds/countdown.mp3", "/static/images/animes/quizz_animes_annees_80.jpg" ],
            "answer_media" : [ "/static/sounds/timeout.mp3", "/static/images/animes/les_attaquantes.jpg" ],
            "wrong_answers" : [ "Basket", "Judo", "Tennis" ],
            "good_answer" : "Volley"
        },
        {
            "question" : "Qui interprète la chanson de générique de 'Pacman' ?",
            "question_timeout" : 5,
            "waiting_answer_timeout": 10,
            "answer_timeout": 3,
            "question_media" : [ "/static/sounds/countdown.mp3", "/static/images/animes/quizz_animes_annees_80.jpg" ],
            "waiting_answer_media" : [ "/static/sounds/countdown.mp3", "/static/images/animes/pac_man.jpg" ],
            "answer_media" : [ "/static/sounds/timeout.mp3", "/static/images/animes/pac_man.jpg" ],
            "wrong_answers" : [ "Antoine de Caunes", "Patrick Sabatier", "Philippe Gildas" ],
            "good_answer" : "William Leymergie"
        },
        {
            "question" : "Quel est le titre français de cet anime ?",
            "question_timeout" : 5,
            "waiting_answer_timeout": 10,
            "answer_timeout": 3,
            "question_media" : [ "/static/sounds/countdown.mp3", "/static/images/animes/brave_starr_nameless.jpg" ],
            "waiting_answer_media" : [ "/static/sounds/countdown.mp3", "/static/images/animes/brave_starr_nameless.jpg" ],
            "answer_media" : [ "/static/sounds/timeout.mp3", "/static/images/animes/brave_starr.jpg" ],
            "wrong_answers" : [ "Cowboy Beebop", "Cosmocats", "Trigun" ],
            "good_answer" : "BraveStarr"
        },
        {
            "question" : "De quel anime viens ce personnage ?",
            "question_timeout" : 5,
            "waiting_answer_timeout": 10,
            "answer_timeout": 3,
            "question_media" : [ "/static/sounds/countdown.mp3", "/static/images/animes/ranma_un_demi_ranma_saotome.jpg" ],
            "waiting_answer_media" : [ "/static/sounds/countdown.mp3", "/static/images/animes/ranma_un_demi_ranma_saotome.jpg" ],
            "answer_media" : [ "/static/sounds/timeout.mp3", "/static/images/animes/ranma_un_demi_logo.jpg" ],
            "wrong_answers" : [ "Judo Boy", "Tom Sawyer", "Sport Billy" ],
            "good_answer" : "Ranma 1/2"
        },
        {
            "question" : "De quel anime viens ce personnage ?",
            "question_timeout" : 5,
            "waiting_answer_timeout": 10,
            "answer_timeout": 3,
            "question_media" : [ "/static/sounds/countdown.mp3", "/static/images/animes/saint_seiya/seiya_de_pegase.jpg" ],
            "waiting_answer_media" : [ "/static/sounds/countdown.mp3", "/static/images/animes/saint_seiya/seiya_de_pegase.jpg" ],
            "answer_media" : [ "/static/sounds/timeout.mp3", "/static/images/animes/saint_seiya/saint_seiya.jpg" ],
            "wrong_answers" : [ "Capitaine Flam", "Les Mondes engloutis", "Goldorak" ],
            "good_answer" : "Les Chevaliers du Zodiaque"
        },
        {
            "question" : "Lequel de ces personnages n'est pas dans Dragon Ball ?",
            "question_timeout" : 5,
            "waiting_answer_timeout": 10,
            "answer_timeout": 3,
            "question_media" : [ "/static/sounds/countdown.mp3", "/static/images/animes/dragon_ball/dragon_ball.jpg" ],
            "waiting_answer_media" : [ "/static/sounds/countdown.mp3", "/static/images/animes/dragon_ball/dragon_ball.jpg" ],
            "answer_media" : [ "/static/sounds/timeout.mp3", "/static/images/animes/naruto/uchiha_itachi.jpg" ],
            "wrong_answers" : [ "San Goku", "Vegeta", "Piccolo" ],
            "good_answer" : "Uchiha Itachi"
        },
        {
            "question" : "Comment se nomme la chèvre préférée de la petite Heidi ?",
            "question_timeout" : 5,
            "waiting_answer_timeout": 10,
            "answer_timeout": 3,
            "question_media" : [ "/static/sounds/countdown.mp3", "/static/images/animes/heidi.jpg" ],
            "waiting_answer_media" : [ "/static/sounds/countdown.mp3", "/static/images/animes/heidi.jpg" ],
            "answer_media" : [ "/static/sounds/timeout.mp3", "/static/images/animes/heidi.jpg" ],
            "wrong_answers" : [ "Pâquerette", "Flocon", "Suzette" ],
            "good_answer" : "Blanchette"
        }
    ]
}
    